kde_material_you_colors/__init__.py
kde_material_you_colors/apply_themes.py
kde_material_you_colors/config.py
kde_material_you_colors/logging_config.py
kde_material_you_colors/main.py
kde_material_you_colors/schemeconfigs.py
kde_material_you_colors/settings.py
kde_material_you_colors/data/kde-material-you-colors-stop.desktop
kde_material_you_colors/data/kde-material-you-colors.desktop
kde_material_you_colors/data/sample_config.conf
kde_material_you_colors/utils/color_utils.py
kde_material_you_colors/utils/config_utils.py
kde_material_you_colors/utils/dbus_utils.py
kde_material_you_colors/utils/extra_image_utils.py
kde_material_you_colors/utils/file_utils.py
kde_material_you_colors/utils/konsole_utils.py
kde_material_you_colors/utils/ksyntax_utils.py
kde_material_you_colors/utils/kwin_utils.py
kde_material_you_colors/utils/m3_scheme_utils.py
kde_material_you_colors/utils/math_utils.py
kde_material_you_colors/utils/notify.py
kde_material_you_colors/utils/plasma_utils.py
kde_material_you_colors/utils/pywal_utils.py
kde_material_you_colors/utils/string_utils.py
kde_material_you_colors/utils/timeout_utils.py
kde_material_you_colors/utils/titlebar_utils.py
kde_material_you_colors/utils/utils.py
kde_material_you_colors/utils/wallpaper_utils.py
kde_material_you_colors-2.0.0.dist-info/licenses/LICENSE
kde_material_you_colors-2.0.0.dist-info/METADATA
kde_material_you_colors-2.0.0.dist-info/WHEEL
kde_material_you_colors-2.0.0.dist-info/entry_points.txt
kde_material_you_colors-2.0.0.dist-info/top_level.txt
kde_material_you_colors-2.0.0.dist-info/RECORD
