Metadata-Version: 2.4
Name: kde-material-you-colors
Version: 2.0.0
Summary: Automatic Material You Colors Generator from your wallpaper for the Plasma Desktop
Author-email: Luis Bocanegra <luisbocanegra17b@gmail.com>
Project-URL: Homepage, https://github.com/luisbocanegra/kde-material-you-colors
Project-URL: Repository, https://github.com/luisbocanegra/kde-material-you-colors
Project-URL: Bug Tracker, https://github.com/luisbocanegra/kde-material-you-colors/issues
Classifier: Programming Language :: Python :: 3
Classifier: License :: OSI Approved :: GNU General Public License v3 (GPLv3)
Classifier: Topic :: Desktop Environment :: K Desktop Environment (KDE) :: Themes
Classifier: Environment :: X11 Applications :: KDE
Classifier: Operating System :: POSIX :: Linux
Requires-Python: >=3.8
License-File: LICENSE
Requires-Dist: dbus-python>=1.3.2
Requires-Dist: numpy>=1.20
Requires-Dist: pillow>=9.2.0
Requires-Dist: materialyoucolor>=2.0.8
Requires-Dist: python-magic>=0.4.27
Provides-Extra: cli
Requires-Dist: pywal16>=3.7.2; extra == "cli"
Dynamic: license-file
